rekall/__init__.py
rekall/_version.py
rekall/addrspace.py
rekall/addrspace_test.py
rekall/algo.py
rekall/args.py
rekall/cache.py
rekall/compatibility.py
rekall/config.py
rekall/constants.py
rekall/interactive.py
rekall/io_manager.py
rekall/io_manager_test.py
rekall/ipython_support.py
rekall/kb.py
rekall/obj.py
rekall/obj_test.py
rekall/plugin.py
rekall/registry.py
rekall/rekal.py
rekall/resources.py
rekall/scan.py
rekall/session.py
rekall/session_test.py
rekall/testlib.py
rekall/tests.py
rekall/threadpool.py
rekall/type_generator.py
rekall/utils.py
rekall/yaml_utils.py
rekall/plugins/__init__.py
rekall/plugins/core.py
rekall/plugins/core_test.py
rekall/plugins/guess_profile.py
rekall/plugins/hypervisors.py
rekall/plugins/imagecopy.py
rekall/plugins/modes.py
rekall/plugins/tests.py
rekall/plugins/yarascanner.py
rekall/plugins/addrspaces/__init__.py
rekall/plugins/addrspaces/accelerated.py
rekall/plugins/addrspaces/aff4.py
rekall/plugins/addrspaces/amd64.py
rekall/plugins/addrspaces/arm.py
rekall/plugins/addrspaces/crash.py
rekall/plugins/addrspaces/elfcore.py
rekall/plugins/addrspaces/ewf.py
rekall/plugins/addrspaces/hibernate.py
rekall/plugins/addrspaces/intel.py
rekall/plugins/addrspaces/lime.py
rekall/plugins/addrspaces/macho.py
rekall/plugins/addrspaces/mips.py
rekall/plugins/addrspaces/mmap_address_space.py
rekall/plugins/addrspaces/pagefile.py
rekall/plugins/addrspaces/pmem.py
rekall/plugins/addrspaces/standard.py
rekall/plugins/addrspaces/vmem.py
rekall/plugins/addrspaces/win32.py
rekall/plugins/addrspaces/xpress.py
rekall/plugins/common/__init__.py
rekall/plugins/common/address_resolver.py
rekall/plugins/common/bovine.py
rekall/plugins/common/inspection.py
rekall/plugins/common/memmap.py
rekall/plugins/common/pas2kas.py
rekall/plugins/common/pfn.py
rekall/plugins/common/profile_index.py
rekall/plugins/common/profile_index_test.py
rekall/plugins/common/scanners.py
rekall_core-1.6.0.dist-info/DESCRIPTION.rst
rekall_core-1.6.0.dist-info/METADATA
rekall_core-1.6.0.dist-info/RECORD
rekall_core-1.6.0.dist-info/WHEEL
rekall_core-1.6.0.dist-info/entry_points.txt
rekall_core-1.6.0.dist-info/metadata.json
rekall_core-1.6.0.dist-info/top_level.txt
