Metadata-Version: 2.0
Name: rekall-core
Version: 1.6.0
Summary: Rekall Memory Forensic Framework
Home-page: https://www.rekall-forensic.com/
Author: The Rekall team
Author-email: rekall-discuss@googlegroups.com
License: GPL
Platform: UNKNOWN
Classifier: Development Status :: 4 - Beta
Classifier: Environment :: Console
Classifier: Operating System :: OS Independent
Classifier: Programming Language :: Python
Requires-Dist: PyYAML (==3.11)
Requires-Dist: acora (==2.0)
Requires-Dist: arrow (==0.7.0)
Requires-Dist: artifacts (==20160114)
Requires-Dist: efilter (==1!1.3)
Requires-Dist: intervaltree (==2.1.0)
Requires-Dist: ipaddr (==2.1.11)
Requires-Dist: psutil (>=4.0,<5.0)
Requires-Dist: pyaff4 (<0.30,>=0.24)
Requires-Dist: pycrypto (==2.6.1)
Requires-Dist: pyelftools (==0.24)
Requires-Dist: pyparsing (==2.1.5)
Requires-Dist: python-dateutil (==2.5.3)
Requires-Dist: pytsk3 (==20160721)
Requires-Dist: pytz (==2016.4)
Requires-Dist: rekall-capstone (==3.0.4.post2)
Requires-Dist: rekall-yara (==3.4.0.1)
Requires-Dist: sortedcontainers (==1.4.4)
Requires-Dist: pypiwin32 (==219); sys_platform=="win32"
